{
  "provider": "notion",
  "schema_version": "lifeos.provider.surface.v1",
  "name": "Notion Adapter Slice",
  "supports": {
    "typed_commands": [
      "wonderfood.create_record",
      "wonderfood.update_record",
      "wonderfood.archive_record"
    ],
    "resolved_data_home": "notion"
  },
  "output_contract": {
    "fields": [
      "success",
      "source_snapshot",
      "provider_record_id",
      "action_receipt"
    ],
    "required_source_snapshot": [
      "provider",
      "data_source_id",
      "page_id",
      "block_id",
      "range"
    ]
  }
}
